punctual/__init__.py
punctual/cli.py
punctual/link.py
punctual/package.py
punctual/utils.py
punctual-1.1.0.dist-info/entry_points.txt
punctual-1.1.0.dist-info/LICENSE
punctual-1.1.0.dist-info/WHEEL
punctual-1.1.0.dist-info/METADATA
punctual-1.1.0.dist-info/RECORD
