Metadata-Version: 2.1
Name: punctual
Version: 1.1.0
Summary: Clean and simple dotfile management with a lot of flexibility
Home-page: https://github.com/markrawls/punctual
Author: Mark Rawls
Author-email: markrawls96@gmail.com
Requires-Python: >=3.7,<4.0
Classifier: Programming Language :: Python :: 3
Classifier: Programming Language :: Python :: 3.7
Requires-Dist: click (>=7.0,<8.0)
Requires-Dist: colorama (>=0.4.1,<0.5.0)
Project-URL: Documentation, https://punctual.readthedocs.io/
Project-URL: Repository, https://github.com/markrawls/punctual
